CHANGES.rst
LICENSE.txt
MANIFEST.in
README.rst
setup.cfg
setup.py
htmloutput/__init__.py
htmloutput/htmloutput.py
nosehtmloutput_2.egg-info/PKG-INFO
nosehtmloutput_2.egg-info/SOURCES.txt
nosehtmloutput_2.egg-info/dependency_links.txt
nosehtmloutput_2.egg-info/entry_points.txt
nosehtmloutput_2.egg-info/requires.txt
nosehtmloutput_2.egg-info/top_level.txt