Metadata-Version: 1.1
Name: nosehtmloutput-2
Version: 1.0
Summary: Nose plugin to produce test results in html.
Home-page: https://github.com/cyraxjoe/nose-html-output
Author: Joel Rivera
Author-email: rivera@joel.mx
License: Apache License, Version 2.0
Download-URL: https://github.com/cyraxjoe/nose-html-output/archive/1.0.zip
Platform: UNKNOWN
Classifier: Environment :: Console
Classifier: Topic :: Software Development :: Testing
Classifier: Intended Audience :: Developers
Classifier: Intended Audience :: Information Technology
Classifier: License :: OSI Approved :: Apache Software License
Classifier: Operating System :: OS Independent
Classifier: Programming Language :: Python
Classifier: Programming Language :: Python :: 3
